gifmaker/__init__.py
gifmaker/gifmaker.py
gifmaker/tests/__init__.py
gifmaker/tests/test_gifmaker.py
gifmaker-1.5.dist-info/LICENSE
gifmaker-1.5.dist-info/METADATA
gifmaker-1.5.dist-info/WHEEL
gifmaker-1.5.dist-info/entry_points.txt
gifmaker-1.5.dist-info/top_level.txt
gifmaker-1.5.dist-info/RECORD
