Metadata-Version: 2.1
Name: gifmaker
Version: 1.5
Summary: Convert a series of images into a gif animation.
Home-page: UNKNOWN
Author: Julien Cohen-Adad
Author-email: jcohen@polymtl.ca
License: LICENSE
Platform: UNKNOWN
Classifier: Programming Language :: Python :: 3
Classifier: License :: OSI Approved :: MIT License
Classifier: Operating System :: OS Independent
Requires-Python: >=3.5
Requires-Dist: imageio
Requires-Dist: scipy
